
{
    "categories": [
        {
            "id": 0,
            "index": 1,
            "number": 1.0,
            "title": "Administration, business and management",
            "code": "admin",
            "children": []
        },
        {
            "id": 0,
            "index": 1,
            "number": 2.0,
            "title": "Financial services",
            "code": "financial",
            "children": [
                {
                    "id": 0,
                    "index": 2,
                    "number": 2.1,
                    "title": "Loan officer",
                    "code": "loan",
                    "children" : []
                },            
                {
                    "id": 0,
                    "index": 2,
                    "number": 2.2,
                    "title": "Operative",
                    "code": "operative",
                    "children" : []
                },            
                {
                    "id": 0,
                    "index": 2,
                    "number": 2.3,
                    "title": "Branch Manager",
                    "code": "branch",
                    "children" : []
                },            
                {
                    "id": 0,
                    "index": 2,
                    "number": 2.4,
                    "title": "External control",
                    "code": "external_control",
                    "children" : []
                },            
                {
                    "id": 0,
                    "index": 2,
                    "number": 2.5,
                    "title": "Leasing",
                    "code": "leasing",
                    "children" : []
                },            
                {
                    "id": 0,
                    "index": 2,
                    "number": 2.6,
                    "title": "Problem loans",
                    "code": "problem_loans",
                    "children" : []
                },
                {
                    "id": 0,
                    "index": 2,
                    "number": 2.7,
                    "title": "Financial Advisor",
                    "code": "financial_dvisor",
                    "children" : []
                }
            ]
        },
        {
            "id": 0,
            "index": 1,
            "number": 3.0,
            "title": "Retail and customer services",
            "code": "retail_customer",
            "children": []
        },
        {
            "id": 0,
            "index": 1,
            "number": 4.0,
            "title": "Engineering",
            "code": "engineering",
            "children": []
        },
        {
            "id": 0,
            "index": 1,
            "number": 5.0,
            "title": "Computing and IT",
            "code": "computing",
            "children": [
                {
                    "id": 0,
                    "index": 2,
                    "number": 5.1,
                    "title": "Web development",
                    "code": "web_development",
                    "children": []
                },
                {
                    "id": 0,
                    "index": 2,
                    "number": 5.2,
                    "title": "Mobile development",
                    "code": "mobile_development",
                    "children": []
                },
                {
                    "id": 0,
                    "index": 2,
                    "number": 5.3,
                    "title": "Network",
                    "code": "network",
                    "children": []
                },
                {
                    "id": 0,
                    "index": 2,
                    "number": 5.4,
                    "title": "Development",
                    "code": "development",
                    "children": []
                },
                {
                    "id": 0,
                    "index": 2,
                    "number": 5.5,
                    "title": "Help desk",
                    "code": "help_desk",
                    "children": []
                },
                {
                    "id": 0,
                    "index": 2,
                    "number": 5.6,
                    "title": "IT security",
                    "code": "it_security",
                    "children": []
                },
                {
                    "id": 0,
                    "index": 2,
                    "number": 5.7,
                    "title": "System administrator",
                    "code": "system_administrator",
                    "children": []
                },
                {
                    "id": 0,
                    "index": 2,
                    "number": 5.8,
                    "title": "QA tester",
                    "code": "qa_tester",
                    "children": []
                },
                {
                    "id": 0,
                    "index": 2,
                    "number": 5.9,
                    "title": "Head of IT",
                    "code": "head_it",
                    "children": []
                }
            ]
        },
        {
            "id": 0,
            "index": 1,
            "number": 6.0,
            "title": "Marketing and advertising, print and publishing",
            "code": "marketing_advertising_print",
            "children": []
        },
        {
            "id": 0,
            "index": 1,
            "number": 7.0,
            "title": "Transport, distribution and logistics",
            "code": "transport_distribution_logistics",
            "children": [
                {
                    "id": 0,
                    "index": 2,
                    "number": 7.1,
                    "title": "Driver",
                    "code": "driver",
                    "children": []
                },
                {
                    "id": 0,
                    "index": 2,
                    "number": 7.2,
                    "title": "Warehouseman",
                    "code": "warehouseman",
                    "children": []
                },
                {
                    "id": 0,
                    "index": 2,
                    "number": 7.3,
                    "title": "Logistics",
                    "code": "logistics",
                    "children": []
                },
                {
                    "id": 0,
                    "index": 2,
                    "number": 7.4,
                    "title": "Courier",
                    "code": "courier",
                    "children": []
                }
            ]
        },
        {
            "id": 0,
            "index": 1,
            "number": 8.0,
            "title": "Healthcare",
            "code": "healthcare",
            "children": [
                {
                    "id": 0,
                    "index": 2,
                    "number": 8.1,
                    "title": "Doctor",
                    "code": "doctor",
                    "children": []
                },
                {
                    "id": 0,
                    "index": 2,
                    "number": 8.2,
                    "title": "Pharmacist",
                    "code": "pharmacist",
                    "children": []
                },
                {
                    "id": 0,
                    "index": 2,
                    "number": 8.3,
                    "title": "Nurse",
                    "code": "nurse",
                    "children": []
                },
                {
                    "id": 0,
                    "index": 2,
                    "number": 8.4,
                    "title": "Psychologist",
                    "code": "psychologist",
                    "children": []
                },
                {
                    "id": 0,
                    "index": 2,
                    "number": 8.5,
                    "title": "Dentist",
                    "code": "dentist",
                    "children": []
                },
                {
                    "id": 0,
                    "index": 2,
                    "number": 8.6,
                    "title": "Laboratory assistant",
                    "code": "laboratory_assistant",
                    "children": []
                },
                {
                    "id": 0,
                    "index": 2,
                    "number": 8.7,
                    "title": "Medicine brother",
                    "code": "medicine_brother",
                    "children": []
                },
                {
                    "id": 0,
                    "index": 2,
                    "number": 8.8,
                    "title": "Medical representative",
                    "code": "medical_representative",
                    "children": []
                }
            ]
        },
        {
            "id": 0,
            "index": 1,
            "number": 9.0,
            "title": "Education and training",
            "code": "education_training",
            "children": []
        },
        {
            "id": 0,
            "index": 1,
            "number": 10.0,
            "title": "Legal and court services",
            "code": "legal_court",
            "children": []
        },
        {
            "id": 0,
            "index": 1,
            "number": 11.0,
            "title": "Facilities and property services",
            "code": "facilities_property",
            "children": []
        },
        {
            "id": 0,
            "index": 1,
            "number": 12.0,
            "title": "Design, arts and crafts",
            "code": "design_arts_crafts",
            "children": [
                {
                    "id": 0,
                    "index": 2,
                    "number": 12.1,
                    "title": "Graphic designer",
                    "code": "graphic_designer",
                    "children": []
                },
                {
                    "id": 0,
                    "index": 2,
                    "number": 12.2,
                    "title": "Interior designer",
                    "code": "interior_designer",
                    "children": []
                }
            ]
        },
        {
            "id": 0,
            "index": 1,
            "number": 13.0,
            "title": "Marketing and Sales",
            "code": "marketing_sales",
            "children": [
                {
                    "id": 0,
                    "index": 2,
                    "number": 13.1,
                    "title": "Content manager",
                    "code": "content_manager",
                    "children": []
                },
                {
                    "id": 0,
                    "index": 2,
                    "number": 13.2,
                    "title": "Seller",
                    "code": "seller",
                    "children": []
                },
                {
                    "id": 0,
                    "index": 2,
                    "number": 13.3,
                    "title": "Sales representative",
                    "code": "sales_representative",
                    "children": []
                },
                {
                    "id": 0,
                    "index": 2,
                    "number": 13.4,
                    "title": "SMM",
                    "code": "smm",
                    "children": []
                },
                {
                    "id": 0,
                    "index": 2,
                    "number": 13.5,
                    "title": "Copywriter",
                    "code": "copywriter",
                    "children": []
                }
            ]
        },
        {
            "id": 0,
            "index": 1,
            "number": 14.0,
            "title": "Chef",
            "code": "chef",
            "children": []
        },
        {
            "id": 0,
            "index": 1,
            "number": 15.0,
            "title": "Service",
            "code": "service",
            "children": [
                {
                    "id": 0,
                    "index": 2,
                    "number": 15.1,
                    "title": "Mechanic",
                    "code": "mechanic",
                    "children": []
                },
                {
                    "id": 0,
                    "index": 2,
                    "number": 15.2,
                    "title": "Technician",
                    "code": "technician",
                    "children": []
                },
                {
                    "id": 0,
                    "index": 2,
                    "number": 15.3,
                    "title": "Electricity",
                    "code": "electricity",
                    "children": []
                },
                {
                    "id": 0,
                    "index": 2,
                    "number": 15.4,
                    "title": "Tour manager",
                    "code": "tour_manager",
                    "children": []
                },
                {
                    "id": 0,
                    "index": 2,
                    "number": 15.5,
                    "title": "Protection",
                    "code": "protection",
                    "children": []
                },
                {
                    "id": 0,
                    "index": 2,
                    "number": 15.6,
                    "title": "Locksmith",
                    "code": "locksmith",
                    "children": []
                },
                {
                    "id": 0,
                    "index": 2,
                    "number": 15.7,
                    "title": "Welder",
                    "code": "welder",
                    "children": []
                },        {
                    "id": 0,
                    "index": 2,
                    "number": 15.8,
                    "title": "Carpenter",
                    "code": "carpenter",
                    "children": []
                }
            ]
        },
        {
            "id": 0,
            "index": 1,
            "number": 16.0,
            "title": "Showman",
            "code": "showman",
            "children": [
                {
                    "id": 0,
                    "index": 2,
                    "number": 16.1,
                    "title": "Musician",
                    "code": "musician",
                    "children": []
                },
                {
                    "id": 0,
                    "index": 2,
                    "number": 16.2,
                    "title": "Singer",
                    "code": "singer",
                    "children": []
                },
                {
                    "id": 0,
                    "index": 2,
                    "number": 16.3,
                    "title": "Dancer",
                    "code": "dancer",
                    "children": []
                },
                {
                    "id": 0,
                    "index": 2,
                    "number": 16.4,
                    "title": "Professional model",
                    "code": "professional_model",
                    "children": []
                }
            ]
        },
        {
            "id": 0,
            "index": 1,
            "number": 17.0,
            "title": "Student",
            "code": "student",
            "children": []
        }
    ],
    "countries": [
        {
        "id": 1,
        "code": "AZ",
        "title": "Azerbaijan"
        },
        {
        "id": 2,
        "code": "GE",
        "title": "Georgia"
        },
        {
        "id": 3,
        "code": "IR",
        "title": "Iran"
        },
        {
        "id": 4,
        "code": "KZ",
        "title": "Kazakhstan"
        },
        {
        "id": 5,
        "code": "KG",
        "title": "Kyrgyzstan"
        },
        {
        "id": 6,
        "code": "TR",
        "title": "Turkey"
        },
        {
        "id": 7,
        "code": "UZ",
        "title": "Uzbekistan"
        }
    ],
    "job_seekers": [
        {
            "id": 1,
            "name": "Ruslana",
            "surname": "Qambayeva",
            "email": "@",
            "employment": "student"
        },    {
            "id": 2,
            "name": "Firuza",
            "surname": "Agayeva",
            "email": "@",
            "employment": "professional_model"
        },    {
            "id": 3,
            "name": "Hakhan",
            "surname": "Erol",
            "email": "@",
            "employment": "financial_advisor"
        },    {
            "id": 4,
            "name": "Samira",
            "surname": "Aliyeva",
            "email": "@",
            "employment": "seller"
        }
    ],
    "offers": [
        {
            "id": 2,
            "employer_id": 2,
            "email": "@",
            "employment": "head_it",
            "ceo": "GOED.MMC",
            "description": "Leads the full product management lifecycle of a new suite of technologies and oversees the team responsible for delivering it. This high-profile role involves working with business leaders and partners across the organization, including C-level executives. Strong business and technology experience in the finance and/or retail domain is essential for success. Oversees the data technology roadmaps of assets and drives the adoption of cutting-edge technologies across the Group, aligned with the enablement mission of the PASHA Holding Data Office. Utilizes experience in Agile organizations to lead, develop, and inspire an Agile delivery team of data engineers, architects, devops engineers’ data operations engineers and data analysts. Foster a culture of innovation and excellence. Mentors and develops data technology team members. Develops and manages the Holding’s data technology roadmap, including requirements, resources, time, cost, quality, risks, and communications, ensuring alignment with the strategic objectives of companies within the Group"
        },
        {
            "id": 3,
            "employer_id": 3,
            "email": "@",
            "employment": "graphic_designer",
            "ceo": "MOOI.MMC",
            "description": "Design and create engaging graphics for various social media platforms (Facebook, Instagram, Twitter, LinkedIn, etc.). Develop and maintain a consistent visual style and brand identity across all social media channels. Collaborate with the marketing team to create graphics for campaigns, promotions, and other marketing materials. Stay up-to-date with the latest design trends and social media best practices. Manage multiple projects simultaneously while meeting deadlines. Create stories for social media. Provide creative input and contribute ideas for social media strategies and campaigns."
        },
        {
            "id": 4,
            "employer_id": 3,
            "email": "@",
            "employment": "chef",
            "ceo": "MOOI.MMC",
            "description": "Prepare existing or future guest food orders under the direct supervision of a supervisor or independently. To ensure the quality of the prepared food, that they meet the required standards. To start work, place ready-made semi-finished products, necessary tools and equipment in the designated work area. Check the cleanliness of all tools, equipment and supplies. Ensuring everything is up to standard. Controlling the meal preparation schedule, prioritizing and executing important tasks during the day. Informing the direct supervisor about the lack of necessary food and supplies for the daily preparation of food. Products and their duration must be constantly monitored. To ensure that the prepared food is of high quality and healthy, and that it meets the required hygienic standards."
        }
    ],
    "freelancers": [
        {
            "id": 1,
            "user": "Avery Davis",
            "email": "@",
            "employment": "nurse"
        },
        {
            "id": 2,
            "user": "Handyman Service",
            "email": "@",
            "employment": "welder"
        },
        {
            "id": 3,
            "user": "Really Great Site",
            "email": "@",
            "employment": "carpenter"
        }
    ],
    "talents": [
        {
            "id": 1,
            "user": "Drum Beats",
            "email": "@",
            "employment": "musician"
        },
        {
            "id": 2,
            "user": "Olivia Wilson",
            "email": "@",
            "employment": "dancer"
        },
        {
            "id": 3,
            "user": "HIP HOP DANCERS",
            "email": "@",
            "employment": "dancer"
        }
    ]
}